{
    "book": "1CH",
    "chapter": 23,
    "verses": {
        "23": "وبَنو موشى ثَلاثةٌ: مَحْلي وعادَرُ ويَريموثُ.",
        "1": "ولمَّا شاخَ داوُدُ وشَبِـعَ مِنَ الأيّامِ أقامَ سُليمانَ ابنَهُ مَلِكا على بَني إِسرائيلَ.",
        "2": "وجمَعَ كُلَّ رؤساءِ إِسرائيلَ وكُلَّ الكهَنةِ واللاَّويِّينَ،",
        "3": "فأحصى اللاَّويِّينَ مِنِ ابنِ ثَلاثينَ سنَةً فما فَوقُ، فكانَ عدَدُهُم ثمانيةً وثَلاثينَ ألفَ رجُلٍ.",
        "4": "فعَيَّنَ مِنهُم أربَعةً وعشرينَ ألفا مُراقبـينَ على بِناءِ هَيكلِ الرّبِّ، وسِتَّةَ آلافِ مُوَظَّفٍ وقاضٍ،",
        "5": "وأربَعةَ آلافِ بَوَّابٍ، وأربَعةَ آلافِ مُنشِدٍ للرّبِّ على آلاتِ التَّسبـيحِ.",
        "6": "وقَسَّمَهُم داوُدُ فِرَقا بِـحسَبِ عشائِرِ بَني لاويِّ الثَّلاثِ: جَرشونَ وقَهاتَ ومَراري.",
        "7": "وكانَ لِجَرشونَ ابنانِ: لَعْدانُ وشَمْعي،",
        "8": "ولِلَعْدانَ ثَلاثةُ بَنينَ: أوَّلُهُم يَحيئيلُ ثُمَّ زيثامُ ويوئيلُ،",
        "9": "ولِشَمْعي ثَلاثةُ بَنينَ: شَلوميثُ وحَزيئيلُ وهارانُ. هؤلاءِ رؤساءُ البـيوتِ والمُنتَسِبةِ للَعْدانَ.",
        "10": "وبَنو شَمْعي أربَعةٌ: يَحَثُ وزينا ويَعوشُ وبَريعةُ.",
        "11": "وكانَ يَحَثُ أوَّلَهُم ثُمَّ زيزا، وأمَّا يَعوشُ وبَريعَةُ فما كانَ لهُما بَنونَ كثيرونَ فَحُسِبوا بَيتا واحدا.",
        "12": "وبَنو قَهاتَ أربَعةٌ: عَمرامُ ويَصهارُ وحبرونُ وعُزِّيئيلُ.",
        "13": "وعَمرامُ ولَدَ هرونَ وموسى. وتكَرَّسَ هرونُ للخِدمةِ في قُدْسِ الأقداسِ هوَ وبَنوهُ إلى الأبدِ: لِـيُوقِدَ البَخورَ أمامَ الرّبِّ ويَخدِمَهُ ويـبارِكَ الشَّعبَ باسمِهِ.",
        "14": "أمَّا موسى رَجُلُ اللهِ، فعُدَّ بَنوهُ في سِبْطِ لاويِّ.",
        "15": "وابنا موسى: جَرشومُ وأليعَزَرُ.",
        "16": "ولِجَرشومَ بَنونَ أوَّلُهُم شَبوئيلُ.",
        "17": "ولأليعَزَرَ ابنٌ واحدٌ: رَحَبْيا، وأمَّا بَنو رَحَبْيا فكانوا كثيرينَ جِدًّا.",
        "18": "وابنُ يَصهارَ: شَلوميثُ وهوَ رئيسُ بَيتِ أبـيهِ.",
        "19": "وبَنو حبرونَ أربَعةٌ: يَرِيَّا أوَّلُهُم ثُمَّ أمُرْيا ويَحْزيئيلُ ويَقمَعامُ.",
        "20": "وابنا عُزِّيئيلَ: ميخا أوَّلُهُما ثُمَّ يَشيَّا.",
        "21": "وابنا مَراري: مَحْلي ومُوشى. وابنا مَحْلي: ألعازارُ وقَيشُ.",
        "22": "وماتَ ألعازارُ ولم يكُنْ لَه بَنونَ بل بَناتٌ، فَتَزَوَّجهنَّ بَنو قَيشَ عَمِّهِنَّ.",
        "24": "هؤلاءِ بَنو لاوي بِـحسَبِ بـيوتِ آبائِهِم وعَشائِرِهِم كما أُحصُوا بأسمائِهِم واحدا واحدا. وتوَلَّى العمَلَ لِخِدمةِ هَيكلِ الرّبِّ كُلُّ مَنْ جاوزَ مِنهُمُ العشرينَ مِنَ العُمرِ،",
        "25": "لأنَّ داوُدَ قالَ: «أراحَ الرّبُّ إلهُ إِسرائيلَ شعبَهُ، وهوَ يَسكُنُ في أورُشليمَ إلى الأبدِ.",
        "26": "فلن يَحمِلَ اللاَّويُّونَ مِنْ بَعدُ مَسكِنَهُ ولا أيَّ شيءٍ يُستَعمَلُ لِخِدمَتِهِ».",
        "27": "لِهذا: أُحصيَ بَنو لاويّ مِنِ ابنِ عشرينَ فما فَوقُ،",
        "28": "فكانوا تَحتَ تَصَرُّفِ بَني هرونَ لِخِدمةِ هَيكلِ الرّبِّ، ولِلعنايةِ بالدُّورِ والغُرَفِ وتَطهيرِ كُلِّ شيءٍ مُقدَّسٍ لِلعبادةِ،",
        "29": "وللمُساعَدةِ في تأمينِ الخُبزِ وسميذِ التَّقدِمةِ ورِقاقِ الفطيرِ وما يُخبَزُ على الصَّاجِ ويُعجَنُ بالزَّيتِ. وكذلِكَ في كُلِّ كَيلٍ وقياسٍ،",
        "30": "ولِلحُضورِ كُلَّ صباحٍ ومساءٍ لِحَمدِ الرّبِّ وتَسبـيحِهِ،",
        "31": "ولِتَقديمِ مُحرَقاتِ الرّبِّ في أيّامِ السَّبتِ ورُؤوسِ الشُّهورِ والأعيادِ، بِـحسَبِ العدَدِ المَفروضِ علَيهِم دائما أمامَ الرّبِّ،",
        "32": "ولِلقيامِ بِـحِراسةِ خَيمةِ الاجتماعِ وآنيةِ اللهِ المُقَدَّسةِ، وحِراسةِ بَني هرونَ أنسِبائِهِم في خِدمةِ هَيكلِ الرّبِّ."
    }
}