{
    "book": "2CH",
    "chapter": 22,
    "verses": {
        "22": "أخزيا ملك يهوذا (",
        "29": ")",
        "1": "فأقامَ سُكَّانُ أورُشليمَ أخَزْيا بنَ يورامَ الأصغَرَ مَلِكا مكانَ أبـيهِ، لأنَّ الغُزاةَ الّذينَ جاؤُوا معَ العربِ إلى المُعَسكرِ قتَلوا جميعَ بَنيهِ الكِبار.",
        "2": "وكانَ أخَزْيا ابنَ عِشرينَ سنَةً حينَ ملَكَ، وملَكَ سنَةً واحدَةً بِأورُشليمَ، وكانَ اسمُ أُمِّهِ عثَلْيا بِنتَ عَمري.",
        "3": ")",
        "4": "ففعَلَ الشَّرَّ في نظَرِ الرّبِّ كنَسلِ أخابَ، الّذينَ كانوا مُستَشاريهِ بَعدَ موتِ أبـيهِ، مِمَّا أدَّى إلى هلاكِهِ.",
        "5": "فسَلَكَ بِـحسَبِ مَشورَتِهِم حينَ خرَجَ معَ يورامَ بنِ أخابَ مَلِكِ إِسرائيلَ لِقِتالِ حَزائيلَ مَلِكِ آرامَ في راموثَ جِلعادَ. وهُناكَ أصابَ الآراميُّونَ يورامَ بِـجِراحٍ،",
        "6": "فرجَعَ إلى يزرَعيلَ ليَتَعالَجَ مِنْ جِراحِهِ، فزارَهُ أخَزْيا هُناكَ في مرَضِهِ.",
        "7": "فكانَت مشيئَةُ اللهِ أنْ تكونَ هذِهِ الزِّيارةُ إلى يورامَ سبَبا في هلاكِهِ، لأنَّهُ بَعدَها خرَجَ معَ يورامَ لِقِتالِ ياهو بنِ نَمْشي الّذي مسَحَهُ الرّبُّ مَلِكا ليُبـيدَ نَسلَ أخابَ.",
        "8": "وبـينَما كانَ الرّبُّ يستَخدِمُ ياهو لِتَنفيذِ قضائِهِ على نَسلِ أخابَ، لَقيَ ياهو جماعَةً مِنْ أعيانِ يَهوذا وبَني إخوَةِ أخَزْيا المُرافِقينَ لَه فقَتَلَهُم.",
        "9": "وأمرَ ياهو رِجالَهُ بِالبَحثِ عَنْ أخَزْيا، فأمسَكوهُ وهوَ مُختَبِـئٌ في السَّامِرةِ وجاؤُوا بهِ إلى ياهو، فقَتَلوهُ ودفَنوهُ إكراما لِجَدِّهِ المَلِكِ يوشافاطَ الّذي عبَدَ الرّبَّ بكُلِّ قلبِهِ. فلم يَبقَ مِنْ نَسلِ أخَزْيا مَنْ يَقدِرُ على ضَبْطِ شُؤونِ المَملَكةِ. عثليا ملكة يهوذا (",
        "10": "فلمَّا رَأت عثَلْيا أنَّ ابنَها أخَزْيا ماتَ، قتَلَت جميعَ النَّسلِ المَلَكيِّ مِن أهلِ يَهوذا.",
        "11": "لكِنَّ يوشَبْعَةَ بِنتَ المَلِكِ يورامَ وزَوجةَ يُوياداعَ الكاهنِ سرَقَت يوآشَ بنَ أخَزْيا أخيها مِنْ بَينِ سائِرِ الأُمَراءِ المَقتولينَ ووَضَعَتهُ معَ مُرضعَتِهِ في إحدى غُرَفِ النَّومِ في هَيكلِ اللهِ، وبِذلِكَ أنقَذَتهُ مِنْ عثَلْيا.",
        "12": "فأقامَ هُناكَ سِتَّ سِنينَ مُختَبِئا، وعثَلْيا تَملِكُ على البلادِ."
    }
}