{
    "book": "EXO",
    "chapter": 18,
    "verses": {
        "18": "فأنتَ تُتعِبُ نفْسَكَ وتُتعِبُ هذا الشَّعبَ معَكَ، لأنَّ الحِمْلَ أثقَلُ منْ أنْ تَحمِلَهُ وحدَكَ.",
        "1": "وسمِعَ يَثْرونُ كاهنُ مِديانَ وحَمُو موسى بكلِّ ما عمِلَ الرّبُّ لموسى ولإِسرائيلَ شعبِهِ حينَ أخرجَهُم مِنْ مِصْرَ.",
        "2": "وكانَ يَثْرونُ استرجَعَ ابنَتَهُ صَفُّورةَ امرأةَ موسى",
        "3": "وابنَيها اللّذَينِ سَمَّى موسى أحدَهُما جَرشومَ وقالَ: «لأنِّي كنتُ نزيلا في أرضٍ غريـبَةٍ»،",
        "4": "وسَمَّى الآخرَ أليعازَرَ وقالَ: «لأنَّ إلهَ أبـي نصَرَني وأنقَذَني مِنْ سيفِ فِرعَونَ».",
        "5": "فجاءَ يَثْرونُ بهؤلاءِ إلى موسى في البرِّيَّةِ حيثُ كانَ نازلا عِندَ جبَلِ اللهِ.",
        "6": "ولمَّا قيلَ لموسى: «ها حَمُوكَ يَثْرونُ قادِمٌ إليكَ معَ امرَأتِكَ وابنَيكَ،",
        "7": "خرجَ موسى للقائِهِ وسجدَ وقبَّلهُ. واستَفسَرَ كُلُّ واحدٍ مِنهُما عَنْ سلامَةِ الآخَرِ ودَخَلا إلى الخَيمَةِ.",
        "8": "وقَصَّ موسى على حَميّهِ جميعَ ما فعلَ الرّبُّ بفِرعَونَ والمِصْريِّينَ منْ أجلِ بَني إِسرائيلَ، وجميعَ ما نالَهُم مِنَ المَشقَّةِ في الطَّريقِ، وكيفَ أنقَذَهُمُ الرّبُّ.",
        "9": "فسُرَّ يَثْرونُ بما عمِلَه الرّبُّ لبَني إِسرائيلَ مِنْ إحسانٍ فائقٍ، حينَ أنقذَهُم مِنْ أيدي المِصْريِّينَ،",
        "10": "وقالَ يَثْرونُ: «تَباركَ الرّبُّ الّذي نجَّاكُم مِنْ أيدي المِصْريِّينَ ومِنْ يَدِ فِرعَونَ. تَباركَ الرّبُّ الّذي نجَّى شعبَهُ مِنْ تَحتِ أيدي المِصْريِّينَ،",
        "11": "الآنَ علِمتُ أنَّ الرّبَّ أعظمُ مِنْ جميعِ الآلهَةِ، لأنَّه صنَعَ هذا بالمِصْريِّينَ حينَ طغَوا علَيكُم».",
        "12": "وقدَّمَ يَثْرونُ مُحرقَةً وذبائِـحَ للهِ. وجاءَ هرونُ وجميعُ شُيوخِ بَني إِسرائيلَ لِـيأكلوا معَهُ أمامَ مذبَحِ اللهِ. تعيـين القضاة",
        "13": "وجلسَ موسى في اليومِ الثَّاني ليَقضيَ للشَّعبِ، فوقفَ الشَّعبُ أمامَهُ مِنَ الصَّباحِ إلى المساءِ.",
        "14": "فلمَّا رأى يَثْرونُ كُلَّ ما كانَ على موسى أنْ يفعَلَه لِلشَّعبِ قالَ لَه: «ما هذا؟ وما بالُكَ جالسا وحدَكَ لِتَقضيَ لجميعِ الشَّعبِ وهُمْ واقِفونَ أمامَكَ مِنَ الصَّباحِ إلى المساءِ؟»",
        "15": "فأجابَهُ موسى: «يجيءُ إليَّ الشَّعبُّ ليعلَموا إرادةَ اللهِ.",
        "16": "إذا كانَت لهُم دعوى يجيئونَ فأقضي بَينَ الفريقَينِ وأُعَرِّفُهُم فرائِضَ اللهِ وشرائِعَهُ».",
        "17": "فقالَ يَثْرونُ لموسى: «لا خيرَ في ما تعمَلُ.",
        "19": "والآنَ اسْمَعْ نصيحَتي فيكونَ اللهُ معَكَ: كُنْ أنتَ وسيطا للشَّعبِ عِندَ اللهِ ترفعُ إليهِ دعاوِيَهُم،",
        "20": "وتُعلِنُ لهُمُ الفَرائِضَ والشَّرائِعَ، وتُعَرِّفُهُمُ الطَّريقَ الّذي يسلُكونَهُ والنَّهْجَ الّذي ينهَجونَه.",
        "21": "واختَرْ مِنَ الشَّعبِ كُلِّهِ رِجَالا أكْفَاءَ يخافونَ اللهَ وأُمنَاءَ يكرَهونَ الرَّشوةَ، ووَلِّهِم على الشَّعبِ رؤساءَ ألوفٍ ومئاتٍ وخَماسينَ وعَشَراتٍ",
        "22": "يَقضونَ للشَّعبِ في كُلِّ وقتٍ ويرفعونَ إليكَ كُلَّ أمرٍ خطيرٍ ويحكمونَ هُم في كُلِّ أمرٍ صغيرٍ، فيحمِلونَ الحِمْلَ معَكَ ويُخَفِّفونَ عَنكَ.",
        "23": "فإنْ أنتَ عمِلْتَ هكذا وأمَرَكَ اللهُ بهِ. أمكنَكَ الاحتِمالُ، وجميعُ هذا الشَّعبِ ينصَرفونَ إلى بُيوتِهِم بسلامٍ».",
        "24": "فسمِعَ موسى مِنْ يَثْرونَ حَميِّهِ وعمِلَ بكُلِّ ما قالَ لَه.",
        "25": "فاخْتارَ رِجالا أكْفَاءَ مِنْ جميعِ بَني إِسرائيلَ وَوَلاَّهُم على الشَّعبِ رؤساءَ ألوفٍ ومئاتٍ وخَماسينَ وعَشَراتٍ.",
        "26": "فكانوا يَقضونَ للشَّعبِ في كُلِّ وقتٍ، وكُلِّ دعوى صعبةٍ يرفعونَهَا إلى موسى، وكلِّ دعوى بسيطةٍ يحكُمونَ هُم فِـيها.",
        "27": "ثمَّ ودَّعَ يَثْرونُ موسى ورجَعَ إلى أرضِهِ."
    }
}