{
    "book": "JOL",
    "chapter": 3,
    "verses": {
        "3": "وأصنعُ عجائبَ في السَّماءِ وعلى الأرضِ، دَما ونارا وأعمدةَ دُخانٍ،",
        "1": "أفيضُ روحي على كُلِّ بشَرٍ، فيتنبَّأُ بَنوكُم وبَناتُكُم، ويحلَمُ شيوخُكُم أحلاما، ويرَى شُبَّانُكُم رؤىً.",
        "2": "وعلى عبـيدي أيضا، نِساءً ورجالا، أفيضُ روحي في تلكَ الأيّامِ.",
        "4": "فتنقلِبُ الشَّمسُ ظلاما، والقمرُ دَما قَبلَ أنْ يأتيَ يومُ الرّبِّ العظيمُ الهائلُ،",
        "5": "وكُلُّ مَنْ يدعو باسمِ الرّبِّ يخلُصُ. ففي جبَلِ صِهيونَ وفي أورُشليمَ يَنجو مَنْ يَنجو معَ الباقينَ الّذينَ يدعوهُمُ الرّبُّ."
    }
}