{
    "book": "PRO",
    "chapter": 18,
    "verses": {
        "1": "الإنسانُ يسعَى وراءَ رغباتِهِ، ويُشاكِسُ كُلَّ رأيٍ صالحٍ.",
        "2": "البليدُ لا يحتَفِظُ بما يتَبَيَّنُ لهُ، بل يكشِفُ كُلَّ ما في قلبِهِ.",
        "3": "معَ الشِّرِّ هُناكَ الاحتقارُ، ومعَ الهوانِ يكونُ العارُ.",
        "4": "كَلامُ الإنسانِ مياهٌ عميقةٌ، ويُنبوعُ الحِكمةِ نهرٌ فائضٌ.",
        "5": "مُحاباةُ الشِّرِّيرِ لا تَجوزُ، ولا حِرمانُ الصِّدِّيقِ مِنَ العدالةِ.",
        "6": "كَلامُ البليدِ يُثيرُ الخُصومةَ، ويَجلِبُ عليهِ الضَّرْبَ.",
        "7": "كَلامُ البليدِ هلاكُهُ، فهوَ يُوقِعُهُ في الشَّرَكِ.",
        "8": "كَلِماتُ النَمَّامِ كطَعامٍ شهِـيٍّ، يَنزِلُ إلى أعماقِ البَطْنِ.",
        "9": "المُتراخي في كُلِّ ما يعمَلُ، هوَ والشَّحَّاذونَ سَواءٌ.",
        "10": "إسمُ الرّبِّ بُرْجٌ مَنيعٌ، يُهرَعُ إليهِ الصِّدِّيقُ فيأمَنُ.",
        "11": "مالُ الغنيِّ مدينتُهُ المَنيعةُ، وهوَ في ظَنِّهِ سُورٌ مُرتَفِـعٌ.",
        "12": "قَبلَ الخَيـبةِ تَشامُخُ القلبِ، وقَبلَ الكرامةِ التَّواضُعُ.",
        "13": "من يُجيـبُ قَبلَ أن يسمَعَ، فحَظُّهُ الحماقَةُ والهَوانُ.",
        "14": "روحُ الإنسانِ تَسنُدُ ضَعفَهُ، فإذا انكسَرت فمَنْ يُحْيـيها.",
        "15": "قلبُ الفهيم يكتَسِبُ المَعرِفةَ، وأذُنُ الحُكماءِ تَطلبُ العِلمَ.",
        "16": "العطيَّةُ تُوَسِّعُ طريقَ الإنسانِ، وتَهديهِ إلى مَقامِ العُظماءِ.",
        "17": "أوَّلُ المُتكلِّمينَ صادِقٌ في تُهمَتِهِ، إلى أنْ يُناقِشَهُ آخرُ.",
        "18": "القُرعَةُ تُبطِلُ الخُصوماتِ، وتَفصِلُ بَينَ الأقوياءِ.",
        "19": "الأخُ مدينةٌ منيعةٌ، تُخاصِمُهُ فيُغلِقُها دونَكَ.",
        "20": "مَنْ طابَ كَلامُهُ يُجازَى خَيرا، ومِنْ غَلَّةِ ما يقولُهُ يشبَعُ.",
        "21": "الموتُ والحياةُ في يدِ اللِّسانِ، ومَنْ أحبَّ الثَّرثَرَةَ أكلَ ثمَرَها.",
        "22": "مَنْ وجَدَ زَوجةً وجَدَ خَيرا، ونالَ رِضىً مِنَ الرّبِّ.",
        "23": "الفقيرُ يتكلَّمُ بِتَضَرُّعٍ، والغنيُّ يُجاوبُ باعْتِزازٍ.",
        "24": "كثرَةُ الأصحابِ تَضُرُّ، وكم مِنْ مُحبٍّ أقربُ مِنْ أخٍ."
    }
}