{
    "book": "PSA",
    "chapter": 137,
    "verses": {
        "137": "نشيد المنفى",
        "1": "على أنهارِ بابلَ هُناكَ جَلَسنا، فَبكَينا عِندَما تَذكَّرْنا صِهيَونَ.",
        "2": "على الصَّفْصافِ في وسَطِها عَلَّقْنا كَنَّاراتِنا.",
        "3": "هُناكَ طلبَ مِنَّا الّذينَ سَبَونا أنْ نُنشِدَ لهُم، والّذينَ عَذَّبونا أنْ نُفَرِّحَهُم. قالوا: «أنشِدوا لنا مِنْ أناشيدِ صِهيَونَ».",
        "4": "كَيفَ نُنشِدُ نشيدَ الرّبِّ في أرضٍ غريـبةٍ؟",
        "5": "إنْ نَسيتُكِ يا أورُشليمُ فلتَنْسَني يَميني.",
        "6": "لِـيَلتَصِقْ لِساني بِـحَنَكي إنْ كُنتُ لا أذكُرُكِ، إنْ كُنتُ لا أُعلِّي أُورُشليمَ على ذُروةِ فرَحي.",
        "7": "أُذكُرْ يا ربُّ بَني أدومَ يومَ سَقَطَت أُورُشليمُ. قالوا: «اهْدِمُوها، اهْدِمُوها حتّى أساسِها».",
        "8": "با ابنةَ بابلَ الصَّائِرةَ إلى الخَرابِ، هَنيئا لِمَنْ يُعاقِبُكِ على ما فعَلْتِهِ بنا.",
        "9": "هَنيئا لِمَنْ يُمسِكُ أطفالَكِ ويَضرِبُ بِهمِ الصَّخرةَ."
    }
}